jellyfin_mpv_shim/__init__.py
jellyfin_mpv_shim/action_thread.py
jellyfin_mpv_shim/bifdecode.py
jellyfin_mpv_shim/bulk_subtitle.py
jellyfin_mpv_shim/cli_mgr.py
jellyfin_mpv_shim/clients.py
jellyfin_mpv_shim/conf.py
jellyfin_mpv_shim/conffile.py
jellyfin_mpv_shim/constants.py
jellyfin_mpv_shim/event_handler.py
jellyfin_mpv_shim/gui_mgr.py
jellyfin_mpv_shim/i18n.py
jellyfin_mpv_shim/log_utils.py
jellyfin_mpv_shim/media.py
jellyfin_mpv_shim/menu.py
jellyfin_mpv_shim/mouse.lua
jellyfin_mpv_shim/mpv_shim.py
jellyfin_mpv_shim/player.py
jellyfin_mpv_shim/rich_presence.py
jellyfin_mpv_shim/settings_base.py
jellyfin_mpv_shim/svp_integration.py
jellyfin_mpv_shim/syncplay.py
jellyfin_mpv_shim/systray.png
jellyfin_mpv_shim/thumbfast.lua
jellyfin_mpv_shim/timeline.py
jellyfin_mpv_shim/trickplay-osc.lua
jellyfin_mpv_shim/trickplay.py
jellyfin_mpv_shim/update_check.py
jellyfin_mpv_shim/utils.py
jellyfin_mpv_shim/video_profile.py
jellyfin_mpv_shim/win_utils.py
jellyfin_mpv_shim/default_shader_pack/LICENSE.md
jellyfin_mpv_shim/default_shader_pack/README.md
jellyfin_mpv_shim/default_shader_pack/pack-hq.json
jellyfin_mpv_shim/default_shader_pack/pack-next.json
jellyfin_mpv_shim/default_shader_pack/pack.json
jellyfin_mpv_shim/default_shader_pack/shaders/Anime4K_AutoDownscalePre_x2.glsl
jellyfin_mpv_shim/default_shader_pack/shaders/Anime4K_AutoDownscalePre_x4.glsl
jellyfin_mpv_shim/default_shader_pack/shaders/Anime4K_Clamp_Highlights.glsl
jellyfin_mpv_shim/default_shader_pack/shaders/Anime4K_Darken_Fast.glsl
jellyfin_mpv_shim/default_shader_pack/shaders/Anime4K_Darken_HQ.glsl
jellyfin_mpv_shim/default_shader_pack/shaders/Anime4K_Darken_VeryFast.glsl
jellyfin_mpv_shim/default_shader_pack/shaders/Anime4K_Deblur_DoG.glsl
jellyfin_mpv_shim/default_shader_pack/shaders/Anime4K_Deblur_Original.glsl
jellyfin_mpv_shim/default_shader_pack/shaders/Anime4K_Denoise_Bilateral_Mean.glsl
jellyfin_mpv_shim/default_shader_pack/shaders/Anime4K_Denoise_Bilateral_Median.glsl
jellyfin_mpv_shim-2.9.0.dist-info/LICENSE.md
jellyfin_mpv_shim-2.9.0.dist-info/METADATA
jellyfin_mpv_shim-2.9.0.dist-info/WHEEL
jellyfin_mpv_shim-2.9.0.dist-info/entry_points.txt
jellyfin_mpv_shim-2.9.0.dist-info/top_level.txt
jellyfin_mpv_shim-2.9.0.dist-info/RECORD
