Metadata-Version: 2.1
Name: jellyfin-mpv-shim
Version: 2.9.0
Summary: Cast media from Jellyfin Mobile and Web apps to MPV.
Home-page: https://github.com/jellyfin/jellyfin-mpv-shim
Author: Izzie Walton
Author-email: izzie@iwalton.com
License: GPLv3
Classifier: Programming Language :: Python :: 3
Classifier: License :: OSI Approved :: GNU General Public License v3 (GPLv3)
Classifier: Operating System :: OS Independent
Requires-Python: >=3.7
License-File: LICENSE.md
Requires-Dist: jellyfin-apiclient-python (>=1.11.0)
Requires-Dist: python-mpv-jsonipc (>=1.2.0)
Requires-Dist: python-mpv (>=1.0.7)
Requires-Dist: requests
Provides-Extra: all
Requires-Dist: Jinja2 ; extra == 'all'
Requires-Dist: pillow ; extra == 'all'
Requires-Dist: pypresence ; extra == 'all'
Requires-Dist: pystray ; extra == 'all'
Requires-Dist: pywebview (>=3.3.1) ; extra == 'all'
Provides-Extra: discord
Requires-Dist: pypresence ; extra == 'discord'
Provides-Extra: gui
Requires-Dist: pillow ; extra == 'gui'
Requires-Dist: pystray ; extra == 'gui'
Provides-Extra: mirror
Requires-Dist: Jinja2 ; extra == 'mirror'
Requires-Dist: pywebview (>=3.3.1) ; extra == 'mirror'
